setup.py
frigga_snake/__init__.py
frigga_snake/ami.py
frigga_snake/cluster.py
frigga_snake/constants.py
frigga_snake/names.py
frigga_snake.egg-info/PKG-INFO
frigga_snake.egg-info/SOURCES.txt
frigga_snake.egg-info/dependency_links.txt
frigga_snake.egg-info/not-zip-safe
frigga_snake.egg-info/requires.txt
frigga_snake.egg-info/top_level.txt
frigga_snake/tests/__init__.py
frigga_snake/tests/test_ami.py