Metadata-Version: 1.0
Name: frigga-snake
Version: 0.1
Summary: Netflix' Frigga in Python
Home-page: UNKNOWN
Author: Kristian Øllegaard
Author-email: kristian@plecto.com
License: UNKNOWN
Platform: UNKNOWN
